ANNOgesic-1.1.14.data/scripts/annogesic
annogesiclib/TSS_upstream.py
annogesiclib/TSSpredator_parser.py
annogesiclib/args_container.py
annogesiclib/blast_class.py
annogesiclib/change_db_format.py
annogesiclib/check_orphan.py
annogesiclib/check_srna_overlap.py
annogesiclib/circRNA_detection.py
annogesiclib/circrna.py
annogesiclib/color_png.py
annogesiclib/combine_frag_tex.py
annogesiclib/combine_gff.py
annogesiclib/compare_sRNA_sORF.py
annogesiclib/compare_srna_promoter.py
annogesiclib/compare_srna_term.py
annogesiclib/compare_tran_term.py
annogesiclib/controller.py
annogesiclib/converter.py
annogesiclib/coverage_detection.py
annogesiclib/crispr.py
annogesiclib/detect_coverage_term.py
annogesiclib/detect_operon.py
annogesiclib/detect_utr.py
annogesiclib/expression.py
annogesiclib/extract_RBS.py
annogesiclib/extract_psortb.py
annogesiclib/extract_sRNA_info.py
annogesiclib/extract_sec_info.py
annogesiclib/fill_gap.py
annogesiclib/filter_TSS_pro.py
annogesiclib/filter_low_expression.py
annogesiclib/format_fixer.py
annogesiclib/gen_TSS_type.py
annogesiclib/gen_promoter_table.py
annogesiclib/gen_screenshots.py
annogesiclib/gen_srna_output.py
annogesiclib/gen_svg.py
annogesiclib/gen_table_tran.py
annogesiclib/gene_express_analysis.py
annogesiclib/gene_ontology.py
annogesiclib/get_Rfam_ribo.py
annogesiclib/get_input.py
annogesiclib/get_inter_seq.py
annogesiclib/get_polyT.py
annogesiclib/get_srna_poly_u.py
annogesiclib/get_target_fasta.py
annogesiclib/gff3.py
annogesiclib/goterm.py
annogesiclib/helper.py
annogesiclib/lib_reader.py
annogesiclib/map_ribos.py
annogesiclib/meme.py
annogesiclib/merge_feature.py
annogesiclib/merge_manual.py
annogesiclib/merge_rnaplex_rnaup.py
annogesiclib/merge_sRNA.py
annogesiclib/modify_rbs_table.py
annogesiclib/multiparser.py
annogesiclib/operon.py
annogesiclib/optimize.py
annogesiclib/optimize_TSSpredator.py
annogesiclib/output_cutoff_table.py
annogesiclib/overlap.py
annogesiclib/parser_wig.py
annogesiclib/paths.py
annogesiclib/plot_PPI.py
ANNOgesic-1.1.14.dist-info/LICENSE
ANNOgesic-1.1.14.dist-info/METADATA
ANNOgesic-1.1.14.dist-info/WHEEL
ANNOgesic-1.1.14.dist-info/top_level.txt
ANNOgesic-1.1.14.dist-info/RECORD
