Metadata-Version: 2.1
Name: ANNOgesic
Version: 1.1.14
Summary: ANNOgesic - A tool for bacterial/archaeal RNA-Seq based genome annotations
Home-page: https://github.com/Sung-Huan/ANNOgesic
Author: Sung-Huan Yu
Author-email: silasysh@g-mail.nsysu.edu.tw
License: ISC License (ISCL)
Platform: UNKNOWN
Classifier: License :: OSI Approved :: ISC License (ISCL)
Classifier: Operating System :: POSIX
Classifier: Programming Language :: Python :: 3
Classifier: Topic :: Scientific/Engineering :: Bio-Informatics
License-File: LICENSE
Requires-Dist: biopython (>=1.65)
Requires-Dist: matplotlib (>=1.5.0)
Requires-Dist: networkx (>=1.9.1)
Requires-Dist: numpy (>=1.9.2)
